eymos/__init__.py
eymos/logger.py
eymos/service.py
eymos/service_manager.py
eymos/utils.py
eymos/services/__init__.py
eymos/services/camera.py
eymos/services/window.py
eymos-1.1.0.dist-info/LICENSE
eymos-1.1.0.dist-info/METADATA
eymos-1.1.0.dist-info/WHEEL
eymos-1.1.0.dist-info/top_level.txt
eymos-1.1.0.dist-info/RECORD
