Metadata-Version: 2.1
Name: eymos
Version: 1.1.0
Summary: EymOS - Lightweight Middleware for Robotics
Home-page: https://github.com/EymoLabs/eymos
Author: EymoLabs
Author-email: info@dzin.es
License: Custom License
Project-URL: Bug Reports, https://github.com/EymoLabs/eymos/issues
Project-URL: Source, https://github.com/EymoLabs/eymos
Keywords: robotics middleware eymos lightweight
Classifier: Programming Language :: Python :: 3
Classifier: License :: Other/Proprietary License
Classifier: Operating System :: OS Independent
Classifier: Intended Audience :: Developers
Classifier: Intended Audience :: Science/Research
Classifier: Topic :: Software Development :: Libraries
Classifier: Topic :: Scientific/Engineering
Requires-Python: >=3.6
License-File: LICENSE
Requires-Dist: opencv-python >=4.5.3.56
Requires-Dist: Pillow >=8.0.0
